{"namedChunkGroups":{"polyfill":{"name":"polyfill","assets":[{"name":"webpack-runtime-6df36e9c1f8f5b249d85.js","size":4183},{"name":"polyfill-72b219bae196683411be.js","size":82649}],"filteredAssets":0,"assetsSize":86832,"filteredAuxiliaryAssets":2,"auxiliaryAssetsSize":217524},"app":{"name":"app","assets":[{"name":"webpack-runtime-6df36e9c1f8f5b249d85.js","size":4183},{"name":"framework-3e59b0ca76e46f05ca8d.js","size":128977},{"name":"styles.fc86d3a568bd0017c812.css","size":22109},{"name":"app-88d2ca66957bd4e7f39b.js","size":68527}],"filteredAssets":0,"assetsSize":223796,"filteredAuxiliaryAssets":3,"auxiliaryAssetsSize":648320},"component---src-pages-404-js":{"name":"component---src-pages-404-js","assets":[{"name":"commons-538588a9c40497e10bb7.js","size":22076},{"name":"component---src-pages-404-js-72d321677b9b93a2ed5d.js","size":1982}],"filteredAssets":0,"assetsSize":24058,"filteredAuxiliaryAssets":3,"auxiliaryAssetsSize":105281},"component---src-pages-about-js":{"name":"component---src-pages-about-js","assets":[{"name":"commons-538588a9c40497e10bb7.js","size":22076},{"name":"component---src-pages-about-js-fac89bd32d527f1d378d.js","size":6008}],"filteredAssets":0,"assetsSize":28084,"filteredAuxiliaryAssets":3,"auxiliaryAssetsSize":109002},"component---src-pages-get-involved-js":{"name":"component---src-pages-get-involved-js","assets":[{"name":"1bfc9850-3b0a3a44d1e7b71beb33.js","size":2776},{"name":"commons-538588a9c40497e10bb7.js","size":22076},{"name":"component---src-pages-get-involved-js-740ff12d267930591dbb.js","size":4416}],"filteredAssets":0,"assetsSize":29268,"filteredAuxiliaryAssets":4,"auxiliaryAssetsSize":1578472},"component---src-pages-index-js":{"name":"component---src-pages-index-js","assets":[{"name":"commons-538588a9c40497e10bb7.js","size":22076},{"name":"component---src-pages-index-js-ee5ecb9ada69a5218315.js","size":3475}],"filteredAssets":0,"assetsSize":25551,"filteredAuxiliaryAssets":5,"auxiliaryAssetsSize":215001},"component---src-pages-markdown-remark-frontmatter-slug-js":{"name":"component---src-pages-markdown-remark-frontmatter-slug-js","assets":[{"name":"commons-538588a9c40497e10bb7.js","size":22076},{"name":"component---src-pages-markdown-remark-frontmatter-slug-js-59bfc48bac2cff9c895f.js","size":1132}],"filteredAssets":0,"assetsSize":23208,"filteredAuxiliaryAssets":3,"auxiliaryAssetsSize":104080},"component---src-pages-news-js":{"name":"component---src-pages-news-js","assets":[{"name":"commons-538588a9c40497e10bb7.js","size":22076},{"name":"component---src-pages-news-js-6fc38b43e5226c42deff.js","size":1863}],"filteredAssets":0,"assetsSize":23939,"filteredAuxiliaryAssets":3,"auxiliaryAssetsSize":105469}},"assetsByChunkName":{"polyfill":["webpack-runtime-6df36e9c1f8f5b249d85.js","polyfill-72b219bae196683411be.js"],"app":["webpack-runtime-6df36e9c1f8f5b249d85.js","framework-3e59b0ca76e46f05ca8d.js","styles.fc86d3a568bd0017c812.css","app-88d2ca66957bd4e7f39b.js"],"component---src-pages-404-js":["commons-538588a9c40497e10bb7.js","component---src-pages-404-js-72d321677b9b93a2ed5d.js"],"component---src-pages-about-js":["commons-538588a9c40497e10bb7.js","component---src-pages-about-js-fac89bd32d527f1d378d.js"],"component---src-pages-get-involved-js":["1bfc9850-3b0a3a44d1e7b71beb33.js","commons-538588a9c40497e10bb7.js","component---src-pages-get-involved-js-740ff12d267930591dbb.js"],"component---src-pages-index-js":["commons-538588a9c40497e10bb7.js","component---src-pages-index-js-ee5ecb9ada69a5218315.js"],"component---src-pages-markdown-remark-frontmatter-slug-js":["commons-538588a9c40497e10bb7.js","component---src-pages-markdown-remark-frontmatter-slug-js-59bfc48bac2cff9c895f.js"],"component---src-pages-news-js":["commons-538588a9c40497e10bb7.js","component---src-pages-news-js-6fc38b43e5226c42deff.js"]},"childAssetsByChunkName":{}}